{"ffz": {"FeelsOldMan": 0, "Okayge": 0, "Wut": 0, "gachiGASM": 0, "Sadge": 0, "PepeWTF": 0, "4Gitte": 0, "POGGERS": 0, "KEKAYAYA": 0, "OMEGALUL": 0, "NOP": 0, "YEP": 0, "KEKWait": 0, "PauseChamp": 0, "TR4IN": 0, "HYP3": 0, "KEKeLaugh": 0, "Kapp": 0, "WeirdChamp": 0, "PogU": 0, "PogYou": 0, "Pepega": 0, "PepeLaugh": 0, "OkayChamp": 0, "KEKW": 0, "FeelsWeirdMan": 0, "5Head": 0, "3Head": 0, "monkaW": 0, "LULW": 0, "FeelsOkayMan": 0, "POG": 0, "Pog": 0, "widepeepoBlanket": 0, "widePepeLaugh": 0, "monkaGIGA": 0, "PepegaPhone": 0, "monkaEyes": 0, "widepeepoSad": 0, "Pogey": 0, "forsenCD": 0, "FeelsStrongMan": 0, "widepeepoHappy": 0, "PepoG": 0, "HYPERDANSGAMEW": 0, "KKonaW": 0, "SmileW": 0, "HandsUp": 0, "AYAYA": 0, "monkaHmm": 0}, "bttv": {"gachiBASS": 0, "monkaSHAKE": 0, "Clap": 0, "Clap2": 0, "PepePls": 0, "PepeHands": 0, "monkaTOS": 0, "HYPERS": 0, "COGGERS": 0, "HAMMERS": 0, "POGSLIDE": 0, "PepoDance": 0, "HYPERSHAKE": 0, "HYPERCOG": 0, "HYPERCLAP": 0, "KKool": 0, "pepeD": 0, "ricardoFlick": 0, "gachiHYPER": 0, "gachiBOP": 0, "billyReady": 0, "pepeJAM": 0, "peepoArrive": 0, "pepeJAMJAM": 0, "ppOverheat": 0, "pepeDS": 0, "PepoCheer": 0, "PepegaAim": 0, "ppJedi": 0, "peepoClap": 0, "HACKERMANS": 0, "pepeDD": 0, "PEPEDS": 0, "peepoSmash": 0, "peepoBox": 0, "peepoGiggles": 0, "Jammies": 0, "JogChamp": 0, "FeelsSadDitch": 0, "FeelsStrongJAM": 0, "peepoWeirdLeave": 0, "peepoRiot": 0, "peepoRun": 0, "HYPERJAMMER": 0, "peepoReallyHappy": 0, "RAPIDHAM": 0, "ppHop": 0, "BBoomer": 0, "BabyYodaSip": 0, "peepoChat": 0, "Libido": 0, "WeSmart": 0, "RareChar": 0, "EZ": 0, "pepeMeltdown": 0, "PepeWhy": 0, "AYAYABASS": 0, "gachiBLAST": 0, "peepoS": 0, "YAPPP": 0, "peepoShut": 0, "sumSmash": 0, "PepegaShake": 0, "ppCircle": 0, "monkaX": 0, "peepoArriveFinger": 0, "peepoFinger": 0, "peepoLeaveFinger": 0, "KEKWArrive": 0, "KEKWLeave": 0, "peepoLeaveWave": 0, "Leddit": 0, "monkaRUN": 0, "peepoLeave": 0, "monkaSoap": 0, "BLELELE": 0, "monkaCough": 0, "pepeL": 0, "FeelsLateMan": 0, "3Pepekeklul": 0, "WeirdChamping": 0, "bongoTap": 0, "HYPERCLAPHD": 0, "burndancePF": 0, "CuteDog": 0, "pugPls": 0, "ppJAM": 0, "monkaDMCA": 0, "PepegaPls": 0, "MYAAA": 0, "PepegaCredit": 0, "PETTHEPEEPO": 0, "pepeClap": 0, "gachiW": 0, "PeepoJuice": 0, "KEKWDANCE": 0, "ppPoof": 0, "peepoCat": 0, "ModTime": 0, "elmoFire": 0}, "sub": {"emongHeart": 0, "emongDatzrage": 0, "emongHello": 0, "emongFeels": 1, "emongGood": 0, "emongLUL": 0, "emongHUGE": 0, "emongSword": 0, "emongHYPERS": 0, "emongPotato": 0, "emongRage": 0, "emongRein": 0, "emongD": 0, "emongC": 0, "emongL": 0, "emongW": 0, "emongM": 0, "emongJ": 0, "emongSully": 0, "emongGasm": 0, "emongEats": 0, "emongShrug": 0, "emongTrash": 0, "emongCool": 0, "emongS": 0, "emongGlare": 0, "emongFP": 0, "emongCozy": 0, "emongSad": 0, "emongBaby": 0, "emongHi": 0, "emongLurk": 0, "emongThicc": 0, "emongSlam": 0, "emongGun": 0, "emongZ": 0, "emongSmile": 0, "emongWink": 0, "emongKEK": 0, "emongVibe": 0, "emongH": 0, "emongHype": 0, "emongBanger": 0, "emongCry": 0, "emongBaka": 0, "emongAYAYA": 0, "emongSmug": 0, "emongHmm": 0, "emongBan": 0, "emong7": 0, "emongJebaited": 0, "emongChamp": 0}}